docs/conf.py
leonardo_toolset/__init__.py
leonardo_toolset/workflows.py
leonardo_toolset/bin/__init__.py
leonardo_toolset/bin/leonardo_workflow.py
leonardo_toolset/destripe/__init__.py
leonardo_toolset/destripe/constant.py
leonardo_toolset/destripe/core.py
leonardo_toolset/destripe/guided_filter_upsample.py
leonardo_toolset/destripe/loss_term_jax.py
leonardo_toolset/destripe/loss_term_torch.py
leonardo_toolset/destripe/network_jax.py
leonardo_toolset/destripe/network_torch.py
leonardo_toolset/destripe/post_processing.py
leonardo_toolset/destripe/utils.py
leonardo_toolset/destripe/utils_jax.py
leonardo_toolset/destripe/utils_torch.py
leonardo_toolset/destripe/bin/__init__.py
leonardo_toolset/destripe/bin/run_destripe.py
leonardo_toolset/destripe/tests/__init__.py
leonardo_toolset/destripe/tests/test_function.py
leonardo_toolset/fusion/NSCT.py
leonardo_toolset/fusion/__init__.py
leonardo_toolset/fusion/blobs_dog.py
leonardo_toolset/fusion/fuse_det.py
leonardo_toolset/fusion/fuse_illu.py
leonardo_toolset/fusion/utils.py
leonardo_toolset/fusion/bin/__init__.py
leonardo_toolset/fusion/bin/run_fuse_det.py
leonardo_toolset/fusion/bin/run_fuse_illu.py
leonardo_toolset/fusion/templates/fuse_2_det.yaml
leonardo_toolset/fusion/templates/fuse_2_high_res_det.yaml
leonardo_toolset/fusion/templates/fuse_4_det.yaml
leonardo_toolset/fusion/templates/fuse_illu.yaml
leonardo_toolset/fusion/tests/__init__.py
leonardo_toolset/tests/__init__.py
leonardo_toolset/tests/test_function.py
leonardo_toolset-1.1.0.dist-info/licenses/LICENSE
leonardo_toolset-1.1.0.dist-info/METADATA
leonardo_toolset-1.1.0.dist-info/WHEEL
leonardo_toolset-1.1.0.dist-info/entry_points.txt
leonardo_toolset-1.1.0.dist-info/top_level.txt
leonardo_toolset-1.1.0.dist-info/RECORD
