Metadata-Version: 2.4
Name: leonardo_toolset
Version: 1.1.0
Summary: Leonardo: an LSFM image processing toolset
Author-email: Yu Liu <liuyu9671@gmail.com>
License: MIT License
Project-URL: Homepage, https://github.com/peng-lab/leonardo_toolset
Project-URL: Bug Tracker, https://github.com/peng-lab/leonardo_toolset/issues
Project-URL: Documentation, https://github.com/peng-lab/leonardo_toolset#README.md
Project-URL: Source Code, https://github.com/peng-lab/leonardo_toolset
Project-URL: User Support, https://github.com/peng-lab/leonardo_toolset/issues
Keywords: leonardo_toolset
Classifier: Development Status :: 2 - Pre-Alpha
Classifier: Intended Audience :: Developers
Classifier: License :: OSI Approved :: MIT License
Classifier: Natural Language :: English
Classifier: Programming Language :: Python :: 3.10
Classifier: Topic :: Scientific/Engineering :: Image Processing
Requires-Python: >=3.10
License-File: LICENSE
Requires-Dist: jax
Requires-Dist: scikit-image
Requires-Dist: torch
Requires-Dist: torchvision
Requires-Dist: tqdm
Requires-Dist: matplotlib
Requires-Dist: dm-haiku
Requires-Dist: SimpleITK
Requires-Dist: jaxwt
Requires-Dist: ptwt
Requires-Dist: PyWavelets
Requires-Dist: antspyx
Requires-Dist: opencv-python
Requires-Dist: colour
Requires-Dist: open3d
Requires-Dist: h5py
Requires-Dist: bioio<2
Requires-Dist: bioio-tifffile
Requires-Dist: jinja2
Requires-Dist: pyyaml
Requires-Dist: bioio-ome-tiff<1.2
Provides-Extra: dev
Requires-Dist: bump-my-version>=1.1.1; extra == "dev"
Requires-Dist: coverage>=5.1; extra == "dev"
Requires-Dist: ipython>=7.15.0; extra == "dev"
Requires-Dist: m2r2>=0.2.7; extra == "dev"
Requires-Dist: pytest-runner>=5.2; extra == "dev"
Requires-Dist: Sphinx>=3.4.3; extra == "dev"
Requires-Dist: sphinx_rtd_theme>=0.5.1; extra == "dev"
Requires-Dist: tox>=3.15.2; extra == "dev"
Requires-Dist: twine>=3.1.1; extra == "dev"
Requires-Dist: wheel>=0.34.2; extra == "dev"
Provides-Extra: test
Requires-Dist: black>=19.10b0; extra == "test"
Requires-Dist: codecov>=2.1.4; extra == "test"
Requires-Dist: flake8>=3.8.3; extra == "test"
Requires-Dist: flake8-debugger>=3.2.1; extra == "test"
Requires-Dist: pytest>=5.4.3; extra == "test"
Requires-Dist: pytest-cov>=2.9.0; extra == "test"
Requires-Dist: pytest-raises>=0.11; extra == "test"
Requires-Dist: tox>=3.15.2; extra == "test"
Provides-Extra: all
Requires-Dist: bump-my-version>=1.1.1; extra == "all"
Requires-Dist: coverage>=5.1; extra == "all"
Requires-Dist: ipython>=7.15.0; extra == "all"
Requires-Dist: m2r2>=0.2.7; extra == "all"
Requires-Dist: pytest-runner>=5.2; extra == "all"
Requires-Dist: Sphinx>=3.4.3; extra == "all"
Requires-Dist: sphinx_rtd_theme>=0.5.1; extra == "all"
Requires-Dist: tox>=3.15.2; extra == "all"
Requires-Dist: twine>=3.1.1; extra == "all"
Requires-Dist: wheel>=0.34.2; extra == "all"
Requires-Dist: black>=19.10b0; extra == "all"
Requires-Dist: codecov>=2.1.4; extra == "all"
Requires-Dist: flake8>=3.8.3; extra == "all"
Requires-Dist: flake8-debugger>=3.2.1; extra == "all"
Requires-Dist: pytest>=5.4.3; extra == "all"
Requires-Dist: pytest-cov>=2.9.0; extra == "all"
Requires-Dist: pytest-raises>=0.11; extra == "all"
Dynamic: license-file
